setup.py
pyaacv/__init__.py
pyaacv/pyaacv.py
pyaacv.egg-info/PKG-INFO
pyaacv.egg-info/SOURCES.txt
pyaacv.egg-info/dependency_links.txt
pyaacv.egg-info/top_level.txt