Metadata-Version: 2.1
Name: pyaacv
Version: 0.1
Summary: PythonBased
